django_extra_settings-0.14.1.dist-info/licenses/LICENSE.txt
extra_settings/__init__.py
extra_settings/admin.py
extra_settings/apps.py
extra_settings/cache.py
extra_settings/fields.py
extra_settings/forms.py
extra_settings/metadata.py
extra_settings/models.py
extra_settings/settings.py
extra_settings/signals.py
extra_settings/test.py
extra_settings/utils.py
extra_settings/locale/en/LC_MESSAGES/django.mo
extra_settings/locale/en/LC_MESSAGES/django.po
extra_settings/locale/es/LC_MESSAGES/django.mo
extra_settings/locale/es/LC_MESSAGES/django.po
extra_settings/locale/it/LC_MESSAGES/django.mo
extra_settings/locale/it/LC_MESSAGES/django.po
extra_settings/locale/ru/LC_MESSAGES/django.mo
extra_settings/locale/ru/LC_MESSAGES/django.po
extra_settings/locale/zh_Hans/LC_MESSAGES/django.mo
extra_settings/locale/zh_Hans/LC_MESSAGES/django.po
extra_settings/migrations/0001_initial.py
extra_settings/migrations/0002_auto_20200826_1714.py
extra_settings/migrations/0003_modified_upload_to.py
extra_settings/migrations/0004_setting_description.py
extra_settings/migrations/0005_setting_value_json_alter_setting_value_type.py
extra_settings/migrations/0006_setting_validator.py
extra_settings/migrations/0007_alter_settings_validator.py
extra_settings/migrations/0008_auto_20221024_0717.py
extra_settings/migrations/__init__.py
extra_settings/static/extra_settings/css/extra_settings.css
extra_settings/static/extra_settings/js/extra_settings.js
extra_settings/templatetags/__init__.py
extra_settings/templatetags/extra_settings.py
django_extra_settings-0.14.1.dist-info/METADATA
django_extra_settings-0.14.1.dist-info/WHEEL
django_extra_settings-0.14.1.dist-info/top_level.txt
django_extra_settings-0.14.1.dist-info/RECORD
